README.rst
setup.py
fastpip/__init__.py
fastpip/fastpip.py
python_fastpip.egg-info/PKG-INFO
python_fastpip.egg-info/SOURCES.txt
python_fastpip.egg-info/dependency_links.txt
python_fastpip.egg-info/top_level.txt