Metadata-Version: 1.1
Name: python-fastpip
Version: 1.1
Summary: Segmentation Based On Turning Points
Home-page: https://github.com/intelie/python-fastpip
Author: Vitor M. A. da Cruz
Author-email: vitor.mazzi@intelie.com.br
License: Apache 2
Platform: UNKNOWN
Classifier: Topic :: Scientific/Engineering :: Visualization
Classifier: License :: OSI Approved :: Apache Software License
